whisperjf/SubtitlesProcessor.py
whisperjf/__init__.py
whisperjf/__main__.py
whisperjf/alignment.py
whisperjf/asr.py
whisperjf/audio.py
whisperjf/conjunctions.py
whisperjf/diarize.py
whisperjf/transcribe.py
whisperjf/types.py
whisperjf/utils.py
whisperjf/assets/mel_filters.npz
whisperjf/assets/pytorch_model.bin
whisperjf/vads/__init__.py
whisperjf/vads/pyannote.py
whisperjf/vads/silero.py
whisperjf/vads/vad.py
whisperjf-0.1.3.dist-info/METADATA
whisperjf-0.1.3.dist-info/WHEEL
whisperjf-0.1.3.dist-info/entry_points.txt
whisperjf-0.1.3.dist-info/licenses/LICENSE
whisperjf-0.1.3.dist-info/RECORD
